[
    {
        "text": "やってみせて、言って聞かせて、やらせてみて、 ほめてやらねば人は動かじ。\n話し合い、耳を傾け、承認し、任せてやらねば、人は育たず。\nやっている、姿を感謝で見守って、信頼せねば、人は実らず。",
        "tag": "教育",
        "author": "山本 五十六"
    },
    {
        "text": "親が子供に教えなければならないのは\n「転ばない方法」ではなく\nむしろ人間は転んでも何度だって\n立ち上がれるということじゃないか！？",
        "tag": "教育",
        "author": "出典:ハチミツとクローバー"
    },
    {
        "text": "少年老い易く、学成り難し。一寸の光陰軽んずべからず。",
        "tag": "教育",
        "author": "朱子"
    },
    {
        "text": "「君の話すことは、全部本に書いてある。君から学ぶことは何もない」",
        "tag": "教育",
        "author": "出典:グッド・ウィル・ハンティング"
    },
    {
        "text": "一年の希望は春が決める。 一日の希望は晩が、家族の希望は和合が、人生の希望は勤勉が決める",
        "tag": "教育",
        "author": "出典:中国の諺"
    },
    {
        "text": "最高の授業には最高の教師と最高の生徒が必要だ",
        "tag": "教育",
        "author": "読み人知らず"
    },
    {
        "text": "人生は卒業後に自分からどれだけ能動的に働きかけたかで決まる。",
        "tag": "教育",
        "author": "小柴昌俊"
    },
    {
        "text": "賢くなろうとして本や黒板に教えを乞うてはならない。 天と地と林と木の葉とは、本当に子供らを賢くするであろう。",
        "tag": "教育",
        "author": "ヤン・アモス・コメニウス"
    },
    {
        "text": "学生時代に大事なのは、何を学んだかではなくて、どうやって学んだかということ。",
        "tag": "教育",
        "author": "出典:白線流し"
    },
    {
        "text": "塩の辛さ、砂糖の甘さは学問では理解できない だが、なめてみればすぐ分かる。",
        "tag": "教育",
        "author": "松下 幸之助"
    },
    {
        "text": "人は教えることによって、もっともよく学ぶ",
        "tag": "教育",
        "author": "セネカ"
    },
    {
        "text": "教育は科学であってはなりません。それは芸術でなければならないのです。",
        "tag": "教育",
        "author": "シュタイナー"
    },
    {
        "text": "教えることのできない子供というものはない。あるのは子供達にうまく教えられない学校と教師だけである。",
        "tag": "教育",
        "author": "M・アドラー"
    },
    {
        "text": "昨日の思想によって子供を縛るのは教育ではなく訓練である。 明日の思想によって子供を縛るのもまた教育ではなくて訓練である。 教育は訓練ではない。創造である。",
        "tag": "教育",
        "author": "野村芳兵衛"
    },
    {
        "text": "子供は食う権利がある。子供は遊ぶ権利がある。 子供は寝る権利がある。子供は叱られる権利がある。…… ところが本当に子供を叱る人が少なくて、怒る人が多いのである。",
        "tag": "教育",
        "author": "賀川豊彦"
    },
    {
        "text": "教育の過程はそれ自体を超えるいかなる目的ももっていない。 すなわちそれはそれ自体の目的なのだ。",
        "tag": "教育",
        "author": "デューイ"
    },
    {
        "text": "教えるとは 希望を語ること 学ぶとは 誠実を胸に刻むこと",
        "tag": "教育",
        "author": "アラゴン"
    },
    {
        "text": "２０歳だろうが８０歳だろうが、とにかく学ぶことをやめてしまったものは老人である。 学び続ける者は、みな若い。人生において一番大切なこと は、頭を若く保つことだ。",
        "tag": "教育",
        "author": "ヘンリー・フォード"
    },
    {
        "text": "学べば学ぶほど、自分が何も知らなかった事に気づく、気づけば気づくほどまた学びたくなる。",
        "tag": "教育",
        "author": "アルベルト・アインシュタイン"
    },
    {
        "text": "小中学校で教えられることは教育ではない。教育の手段である。",
        "tag": "教育",
        "author": "ラルフ・ワルド・エマーソン"
    },
    {
        "text": "私は常に学んでいる。墓石が私の卒業証書だ。",
        "tag": "教育",
        "author": "アーサー キット"
    },
    {
        "text": "勉強する事は自分の無知を徐々に発見していく事である。",
        "tag": "教育",
        "author": "ウェル デュラント"
    },
    {
        "text": "学校で学んだことを一切忘れてしまった時に、なお残っているもの、それこそ教育だ。",
        "tag": "教育",
        "author": "アインシュタイン"
    },
    {
        "text": "平凡な教師は言って聞かせる。 よい教師は説明する。 優秀な教師はやってみせる。 しかし最高の教師 は子どもの心に火をつける。",
        "tag": "教育",
        "author": "ウィリアム・ウォード"
    },
    {
        "text": "経験は最良の教師である ただし、授業料が高すぎる。",
        "tag": "教育",
        "author": "カーライル"
    },
    {
        "text": "人間はどんなところでも学ぶことができる。 知りたいという心さえあれば",
        "tag": "教育",
        "author": "出典:MASTERキートン"
    },
    {
        "text": "スローペースで走らせるのも大事なのだ",
        "tag": "教育",
        "author": "小出 義雄"
    }
]